LICENSE
MANIFEST.in
README.rst
setup.py
examples/example_mccv_digits.py
examples/example_nn_iris.py
stochannpy/__init__.py
stochannpy/_base_neural_network.py
stochannpy/bayesian_neural_network.py
stochannpy/evolutionary_neural_network.py
stochannpy/mccv.py
stochannpy.egg-info/PKG-INFO
stochannpy.egg-info/SOURCES.txt
stochannpy.egg-info/dependency_links.txt
stochannpy.egg-info/requires.txt
stochannpy.egg-info/top_level.txt
stochannpy/__pycache__/__init__.cpython-36.pyc
stochannpy/__pycache__/_base_neural_network.cpython-36.pyc
stochannpy/__pycache__/bayesian_neural_network.cpython-36.pyc
stochannpy/__pycache__/evolutionary_neural_network.cpython-36.pyc
stochannpy/__pycache__/mccv.cpython-36.pyc