Metadata-Version: 1.1
Name: stochannpy
Version: 0.0.1
Summary: StochANNPy
Home-page: https://github.com/keurfonluu/stochannpy
Author: Keurfon LUU
Author-email: keurfon.luu@mines-paristech.fr
License: MIT License
Platform: UNKNOWN
Classifier: Programming Language :: Python
Classifier: Development Status :: 4 - Beta
Classifier: License :: OSI Approved :: MIT License
Classifier: Natural Language :: English
Classifier: Operating System :: OS Independent
Classifier: Intended Audience :: Science/Research
Classifier: Topic :: Scientific/Engineering
Classifier: Topic :: Scientific/Engineering :: Mathematics
Classifier: Topic :: Scientific/Engineering :: Artificial Intelligence
Classifier: Topic :: Scientific/Engineering :: Image Recognition
